LICENSE
MANIFEST.in
README.rst
requirements.txt
setup.cfg
setup.py
.github/workflows/main.yml
.github/workflows/pypi.yml
doc/Makefile
doc/conf.py
doc/index.rst
sequana_pipelines/quality_control/__init__.py
sequana_pipelines/quality_control/cluster_config.json
sequana_pipelines/quality_control/config.yaml
sequana_pipelines/quality_control/dag.png
sequana_pipelines/quality_control/main.py
sequana_pipelines/quality_control/quality_control.rules
sequana_pipelines/quality_control/requirements.txt
sequana_pipelines/quality_control/schema.yaml
sequana_pipelines/quality_control/data/__init__.py
sequana_pipelines/quality_control/data/phiX174.fa
sequana_quality_control.egg-info/PKG-INFO
sequana_quality_control.egg-info/SOURCES.txt
sequana_quality_control.egg-info/dependency_links.txt
sequana_quality_control.egg-info/entry_points.txt
sequana_quality_control.egg-info/not-zip-safe
sequana_quality_control.egg-info/requires.txt
sequana_quality_control.egg-info/top_level.txt
singularity/Makefile
singularity/Singularity
test/__init__.py
test/test_main.py
test/data/data_R1_.fastq.gz
test/data/data_R2_.fastq.gz
test/data/phiX174.fa
test/quality_control/quality_control.rules
test/quality_control/test.rules
test/quality_control/.sequana/quality_control.rules
test/quality_control/data/report_qc_data/inputs/quality_control.rules